README.md
tomlantic/__init__.py
tomlantic/py.typed
tomlantic/tomlantic.py
tomlantic-0.2.1.dist-info/METADATA
tomlantic-0.2.1.dist-info/WHEEL
tomlantic-0.2.1.dist-info/RECORD
