Metadata-Version: 2.1
Name: tomlantic
Version: 0.2.1
Summary: marrying pydantic models and tomlkit documents
License: Unlicense
Author: Mark Joshwel
Author-email: mark@joshwel.co
Requires-Python: >=3.8,<4.0
Classifier: License :: OSI Approved
Classifier: Programming Language :: Python :: 3
Classifier: Programming Language :: Python :: 3.8
Classifier: Programming Language :: Python :: 3.9
Classifier: Programming Language :: Python :: 3.10
Classifier: Programming Language :: Python :: 3.11
Classifier: Programming Language :: Python :: 3.12
Requires-Dist: pydantic (>=2.0)
Requires-Dist: tomlkit (>=0.8)
